pystrom/__init__.py
pystrom/__main__.py
pystrom/console.py
pystrom/device.py
pystrom/exceptions.py
pystrom/finder.py
pystrom-2.1.0.dist-info/licenses/LICENSE
pystrom-2.1.0.dist-info/METADATA
pystrom-2.1.0.dist-info/WHEEL
pystrom-2.1.0.dist-info/top_level.txt
pystrom-2.1.0.dist-info/RECORD
