Metadata-Version: 2.4
Name: pystrom
Version: 2.1.0
Summary: Unofficial MyStrom API Client
Author-email: Rafael Urben <github@rafaelurben.ch>
Maintainer-email: Rafael Urben <github@rafaelurben.ch>
License: Copyright (c) 2025 Rafael Urben
Project-URL: Homepage, https://github.com/rafaelurben/python-mystrom
Project-URL: GitHub, https://github.com/rafaelurben/python-mystrom
Project-URL: Issues, https://github.com/rafaelurben/python-mystrom/issues
Classifier: License :: OSI Approved :: MIT License
Classifier: Operating System :: OS Independent
Classifier: Programming Language :: Python
Classifier: Programming Language :: Python :: 3
Classifier: Programming Language :: Python :: 3 :: Only
Classifier: Programming Language :: Python :: 3.11
Classifier: Programming Language :: Python :: 3.12
Classifier: Programming Language :: Python :: 3.13
Requires-Python: >=3.11
License-File: LICENSE
Requires-Dist: requests>=2.25.1
Requires-Dist: packaging>=20.8
Provides-Extra: dev
Requires-Dist: black>=25.1.0; extra == "dev"
Requires-Dist: mypy>=1.16.1; extra == "dev"
Dynamic: license-file
